{
    "n_drivers": 2,
    "n_requests": 6,
    "n_yards": 1,
    "n_configs": 20,
    "params": {
        "cost_driving_km": 1.5,
        "cost_driver_min": 0.5,
        "distance_factor": 1.0,
        "average_speed_km_h": 60.0,
        "time_horizon": 1440.0,
        "max_work_duration_min": 900.0,
        "max_work_duration_reduced_min": 720.0,
        "reduced_time_boundary": 300.0,
        "yard_changeover_time_min": 30.0,
        "max_yard_visits_per_driver": 3,
        "distanceCalculationMethod": "Haversine"
    },
    "assets": [
        {
            "idx": 0,
            "name": "TR.tr1.empt",
            "resource_type": "TR",
            "is_chassis": false,
            "is_full": false,
            "is_empt": true,
            "is_none": false
        },
        {
            "idx": 1,
            "name": "TR.tr1.full",
            "resource_type": "TR",
            "is_chassis": false,
            "is_full": true,
            "is_empt": false,
            "is_none": false
        },
        {
            "idx": 2,
            "name": "SB.sb1.empt",
            "resource_type": "SB",
            "is_chassis": false,
            "is_full": false,
            "is_empt": true,
            "is_none": false
        },
        {
            "idx": 3,
            "name": "SB.sb1.full",
            "resource_type": "SB",
            "is_chassis": false,
            "is_full": true,
            "is_empt": false,
            "is_none": false
        },
        {
            "idx": 4,
            "name": "Truck",
            "resource_type": "",
            "is_chassis": true,
            "is_full": false,
            "is_empt": false,
            "is_none": false
        },
        {
            "idx": 5,
            "name": "Hangr",
            "resource_type": "",
            "is_chassis": true,
            "is_full": false,
            "is_empt": false,
            "is_none": false
        },
        {
            "idx": 6,
            "name": "Dolly",
            "resource_type": "",
            "is_chassis": true,
            "is_full": false,
            "is_empt": false,
            "is_none": false
        },
        {
            "idx": 7,
            "name": "Tract",
            "resource_type": "",
            "is_chassis": true,
            "is_full": false,
            "is_empt": false,
            "is_none": false
        },
        {
            "idx": 8,
            "name": "Bdoub",
            "resource_type": "",
            "is_chassis": true,
            "is_full": false,
            "is_empt": false,
            "is_none": false
        }
    ],
    "configurations": [
        {
            "idx": 0,
            "name": "Truck<SB.sb1.empt>",
            "emission_factor": 1.0
        },
        {
            "idx": 1,
            "name": "Truck<SB.sb1.full>",
            "emission_factor": 1.1
        },
        {
            "idx": 2,
            "name": "Truck<SB.sb1.empt>_Hangr<SB.sb1.empt>",
            "emission_factor": 1.3
        },
        {
            "idx": 3,
            "name": "Truck<SB.sb1.empt>_Hangr<SB.sb1.full>",
            "emission_factor": 1.4
        },
        {
            "idx": 4,
            "name": "Truck<SB.sb1.full>_Hangr<SB.sb1.empt>",
            "emission_factor": 1.4
        },
        {
            "idx": 5,
            "name": "Truck<SB.sb1.full>_Hangr<SB.sb1.full>",
            "emission_factor": 1.5
        },
        {
            "idx": 6,
            "name": "Truck<SB.sb1.empt>_Dolly<TR.tr1.empt>",
            "emission_factor": 1.3
        },
        {
            "idx": 7,
            "name": "Truck<SB.sb1.empt>_Dolly<TR.tr1.full>",
            "emission_factor": 1.4
        },
        {
            "idx": 8,
            "name": "Truck<SB.sb1.full>_Dolly<TR.tr1.empt>",
            "emission_factor": 1.4
        },
        {
            "idx": 9,
            "name": "Truck<SB.sb1.full>_Dolly<TR.tr1.full>",
            "emission_factor": 1.5
        },
        {
            "idx": 10,
            "name": "Tract<TR.tr1.empt>",
            "emission_factor": 1.0
        },
        {
            "idx": 11,
            "name": "Tract<TR.tr1.full>",
            "emission_factor": 1.1
        },
        {
            "idx": 12,
            "name": "Tract<TR.tr1.empt>_Hangr<SB.sb1.empt>",
            "emission_factor": 1.3
        },
        {
            "idx": 13,
            "name": "Tract<TR.tr1.empt>_Hangr<SB.sb1.full>",
            "emission_factor": 1.4
        },
        {
            "idx": 14,
            "name": "Tract<TR.tr1.full>_Hangr<SB.sb1.empt>",
            "emission_factor": 1.4
        },
        {
            "idx": 15,
            "name": "Tract<TR.tr1.full>_Hangr<SB.sb1.full>",
            "emission_factor": 1.5
        },
        {
            "idx": 16,
            "name": "Tract<SB.sb1.empt>_Bdoub<TR.tr1.empt>",
            "emission_factor": 1.3
        },
        {
            "idx": 17,
            "name": "Tract<SB.sb1.empt>_Bdoub<TR.tr1.full>",
            "emission_factor": 1.4
        },
        {
            "idx": 18,
            "name": "Tract<SB.sb1.full>_Bdoub<TR.tr1.empt>",
            "emission_factor": 1.4
        },
        {
            "idx": 19,
            "name": "Tract<SB.sb1.full>_Bdoub<TR.tr1.full>",
            "emission_factor": 1.5
        }
    ],
    "drivers": [
        {
            "idx": 0,
            "name": "driver_0",
            "start_configuration_idx": 10,
            "sleeps_on_road": true,
            "earliest_start_time": 194.0,
            "fixed_cost": 0.0,
            "coordinates_start": [
                0.19487207,
                -0.27576982
            ],
            "coordinates_end": [
                -0.3578118,
                0.30890836
            ],
            "loaded_orders": [],
            "start_loaded_customers": []
        },
        {
            "idx": 1,
            "name": "driver_1",
            "start_configuration_idx": 10,
            "sleeps_on_road": true,
            "earliest_start_time": 273.0,
            "fixed_cost": 0.0,
            "coordinates_start": [
                0.43692405,
                0.44165678
            ],
            "coordinates_end": [
                -0.47349253,
                0.43896534
            ],
            "loaded_orders": [],
            "start_loaded_customers": []
        }
    ],
    "nodes": [
        {
            "idx": 0,
            "name": "cust_0_tomorrow_pick",
            "order_number": 0,
            "customer_type": 8,
            "event_type": "LLD",
            "request_idx": 0,
            "request_homogeneous": false,
            "request_penalty": 1000.0,
            "service_time": 0.0,
            "additional_distance": 0.0,
            "additional_time": 0.0,
            "coordinates": [
                0.45575397,
                -0.32703389
            ],
            "time_window": [
                0.0,
                1440.0
            ]
        },
        {
            "idx": 1,
            "name": "cust_1_tomorrow_del",
            "order_number": 0,
            "customer_type": 9,
            "event_type": "DRL",
            "request_idx": 0,
            "request_homogeneous": false,
            "request_penalty": 1000.0,
            "service_time": 0.0,
            "additional_distance": 0.0,
            "additional_time": 0.0,
            "coordinates": [
                -0.3864753,
                -0.14401939
            ],
            "time_window": [
                0.0,
                1440.0
            ]
        },
        {
            "idx": 2,
            "name": "cust_2",
            "order_number": 1,
            "customer_type": 4,
            "event_type": "HPL",
            "request_idx": 1,
            "request_homogeneous": false,
            "request_penalty": 1000.0,
            "service_time": 17.0,
            "additional_distance": 0.0,
            "additional_time": 0.0,
            "coordinates": [
                -0.08030827,
                0.20732621
            ],
            "time_window": [
                376.5932319645776,
                711.5932319645776
            ]
        },
        {
            "idx": 3,
            "name": "cust_3",
            "order_number": 1,
            "customer_type": 5,
            "event_type": "LUL",
            "request_idx": 1,
            "request_homogeneous": false,
            "request_penalty": 1000.0,
            "service_time": 21.0,
            "additional_distance": 0.0,
            "additional_time": 0.0,
            "coordinates": [
                0.2308525,
                0.36490877
            ],
            "time_window": [
                629.980582323978,
                845.980582323978
            ]
        },
        {
            "idx": 4,
            "name": "cust_4",
            "order_number": 2,
            "customer_type": 4,
            "event_type": "HPL",
            "request_idx": 2,
            "request_homogeneous": false,
            "request_penalty": 1000.0,
            "service_time": 40.0,
            "additional_distance": 0.0,
            "additional_time": 0.0,
            "coordinates": [
                0.15491324,
                0.42136962
            ],
            "time_window": [
                650.2202550097829,
                814.2202550097829
            ]
        },
        {
            "idx": 5,
            "name": "cust_5",
            "order_number": 2,
            "customer_type": 5,
            "event_type": "DRL",
            "request_idx": 2,
            "request_homogeneous": false,
            "request_penalty": 1000.0,
            "service_time": 46.0,
            "additional_distance": 0.0,
            "additional_time": 0.0,
            "coordinates": [
                0.23616846,
                0.16577609
            ],
            "time_window": [
                1147.8936057690632,
                1440.0
            ]
        },
        {
            "idx": 6,
            "name": "cust_6_loaded_end_pick",
            "order_number": 3,
            "customer_type": 6,
            "event_type": "LLD",
            "request_idx": 3,
            "request_homogeneous": false,
            "request_penalty": 1000.0,
            "service_time": 32.0,
            "additional_distance": 0.0,
            "additional_time": 0.0,
            "coordinates": [
                0.28469226,
                -0.26057223
            ],
            "time_window": [
                590.2244239906995,
                694.2244239906995
            ]
        },
        {
            "idx": 7,
            "name": "cust_7_loaded_end_del",
            "order_number": 3,
            "customer_type": 7,
            "event_type": "DRL",
            "request_idx": 3,
            "request_homogeneous": false,
            "request_penalty": 1000.0,
            "service_time": 0.0,
            "additional_distance": 0.0,
            "additional_time": 0.0,
            "coordinates": [
                0.19219044,
                -0.49943332
            ],
            "time_window": [
                0.0,
                1440.0
            ]
        },
        {
            "idx": 8,
            "name": "cust_8",
            "order_number": 4,
            "customer_type": 4,
            "event_type": "HPL",
            "request_idx": 4,
            "request_homogeneous": false,
            "request_penalty": 1000.0,
            "service_time": 31.0,
            "additional_distance": 0.0,
            "additional_time": 0.0,
            "coordinates": [
                -0.20665365,
                0.173081
            ],
            "time_window": [
                638.1509436869637,
                729.1509436869637
            ]
        },
        {
            "idx": 9,
            "name": "cust_9",
            "order_number": 4,
            "customer_type": 5,
            "event_type": "DRL",
            "request_idx": 4,
            "request_homogeneous": false,
            "request_penalty": 1000.0,
            "service_time": 56.0,
            "additional_distance": 0.0,
            "additional_time": 0.0,
            "coordinates": [
                0.38758797,
                -0.16008707
            ],
            "time_window": [
                871.6648537383983,
                1062.6648537383983
            ]
        },
        {
            "idx": 10,
            "name": "cust_10",
            "order_number": 5,
            "customer_type": 4,
            "event_type": "LLD",
            "request_idx": 5,
            "request_homogeneous": false,
            "request_penalty": 1000.0,
            "service_time": 47.0,
            "additional_distance": 0.0,
            "additional_time": 0.0,
            "coordinates": [
                0.08561589,
                -0.22598922
            ],
            "time_window": [
                695.8146299496011,
                1015.8146299496011
            ]
        },
        {
            "idx": 11,
            "name": "cust_11",
            "order_number": 5,
            "customer_type": 5,
            "event_type": "LUL",
            "request_idx": 5,
            "request_homogeneous": false,
            "request_penalty": 1000.0,
            "service_time": 45.0,
            "additional_distance": 0.0,
            "additional_time": 0.0,
            "coordinates": [
                0.298754,
                -0.45620766
            ],
            "time_window": [
                929.3529640081633,
                1157.3529640081633
            ]
        }
    ],
    "yards": [
        {
            "idx": 0,
            "name": "yard_0",
            "coordinates": [
                0.46426582,
                -0.21262435
            ]
        }
    ],
    "configurations_graph": {
        "4,2": [
            5
        ],
        "4,6": [
            9
        ],
        "4,12": [
            15
        ],
        "4,16": [
            19
        ],
        "5,5": [
            2
        ],
        "5,9": [
            6
        ],
        "5,15": [
            12
        ],
        "5,19": [
            16
        ],
        "6,2": [
            5
        ],
        "6,6": [
            9
        ],
        "6,12": [
            15
        ],
        "6,16": [
            19
        ],
        "7,5": [
            2
        ],
        "7,9": [
            6
        ],
        "7,15": [
            12
        ],
        "7,19": [
            16
        ],
        "8,2": [
            5
        ],
        "8,6": [
            9
        ],
        "8,12": [
            15
        ],
        "8,16": [
            19
        ],
        "9,5": [
            2
        ],
        "9,9": [
            6
        ],
        "9,15": [
            12
        ],
        "9,19": [
            16
        ],
        "10,6": [
            7
        ],
        "10,8": [
            9
        ],
        "10,10": [
            11
        ],
        "10,12": [
            14
        ],
        "10,13": [
            15
        ],
        "10,16": [
            17
        ],
        "10,18": [
            19
        ],
        "11,7": [
            6
        ],
        "11,9": [
            8
        ],
        "11,11": [
            10
        ],
        "11,14": [
            12
        ],
        "11,15": [
            13
        ],
        "11,17": [
            16
        ],
        "11,19": [
            18
        ],
        "12,0": [
            1
        ],
        "12,2": [
            4,
            3
        ],
        "12,3": [
            5
        ],
        "12,4": [
            5
        ],
        "12,6": [
            8
        ],
        "12,7": [
            9
        ],
        "12,12": [
            13
        ],
        "12,14": [
            15
        ],
        "12,16": [
            18
        ],
        "12,17": [
            19
        ],
        "13,1": [
            0
        ],
        "13,3": [
            2
        ],
        "13,4": [
            2
        ],
        "13,5": [
            3,
            4
        ],
        "13,8": [
            6
        ],
        "13,9": [
            7
        ],
        "13,13": [
            12
        ],
        "13,15": [
            14
        ],
        "13,18": [
            16
        ],
        "13,19": [
            17
        ],
        "14,0": [
            1
        ],
        "14,2": [
            4,
            3
        ],
        "14,3": [
            5
        ],
        "14,4": [
            5
        ],
        "14,6": [
            8
        ],
        "14,7": [
            9
        ],
        "14,12": [
            13
        ],
        "14,14": [
            15
        ],
        "14,16": [
            18
        ],
        "14,17": [
            19
        ],
        "15,1": [
            0
        ],
        "15,3": [
            2
        ],
        "15,4": [
            2
        ],
        "15,5": [
            3,
            4
        ],
        "15,8": [
            6
        ],
        "15,9": [
            7
        ],
        "15,13": [
            12
        ],
        "15,15": [
            14
        ],
        "15,18": [
            16
        ],
        "15,19": [
            17
        ]
    },
    "search_for_empty": [
        "empt"
    ],
    "search_for_full": [
        "full"
    ],
    "z_requirements_config_loc": [
        [
            true,
            true,
            true,
            true,
            true,
            true,
            true,
            true,
            true,
            true,
            true,
            true
        ],
        [
            true,
            true,
            true,
            true,
            true,
            true,
            true,
            true,
            true,
            true,
            true,
            true
        ],
        [
            true,
            true,
            true,
            true,
            true,
            true,
            true,
            true,
            true,
            true,
            true,
            true
        ],
        [
            true,
            true,
            true,
            true,
            true,
            true,
            true,
            true,
            true,
            true,
            true,
            true
        ],
        [
            true,
            true,
            true,
            true,
            true,
            true,
            true,
            true,
            true,
            true,
            true,
            true
        ],
        [
            true,
            true,
            true,
            true,
            true,
            true,
            true,
            true,
            true,
            true,
            true,
            true
        ],
        [
            true,
            true,
            true,
            true,
            true,
            true,
            true,
            true,
            true,
            true,
            true,
            true
        ],
        [
            true,
            true,
            true,
            true,
            true,
            true,
            true,
            true,
            true,
            true,
            true,
            true
        ],
        [
            true,
            true,
            true,
            true,
            true,
            true,
            true,
            true,
            true,
            true,
            true,
            true
        ],
        [
            true,
            true,
            true,
            true,
            true,
            true,
            true,
            true,
            true,
            true,
            true,
            true
        ],
        [
            true,
            true,
            true,
            true,
            true,
            true,
            true,
            true,
            true,
            true,
            true,
            true
        ],
        [
            true,
            true,
            true,
            true,
            true,
            true,
            true,
            true,
            true,
            true,
            true,
            true
        ],
        [
            true,
            true,
            true,
            true,
            true,
            true,
            true,
            true,
            true,
            true,
            true,
            true
        ],
        [
            true,
            true,
            true,
            true,
            true,
            true,
            true,
            true,
            true,
            true,
            true,
            true
        ],
        [
            true,
            true,
            true,
            true,
            true,
            true,
            true,
            true,
            true,
            true,
            true,
            true
        ],
        [
            true,
            true,
            true,
            true,
            true,
            true,
            true,
            true,
            true,
            true,
            true,
            true
        ],
        [
            true,
            true,
            true,
            true,
            true,
            true,
            true,
            true,
            true,
            true,
            true,
            true
        ],
        [
            true,
            true,
            true,
            true,
            true,
            true,
            true,
            true,
            true,
            true,
            true,
            true
        ],
        [
            true,
            true,
            true,
            true,
            true,
            true,
            true,
            true,
            true,
            true,
            true,
            true
        ],
        [
            true,
            true,
            true,
            true,
            true,
            true,
            true,
            true,
            true,
            true,
            true,
            true
        ]
    ],
    "z_requirements_driver_config": [
        [
            true,
            true,
            true,
            true,
            true,
            true,
            true,
            true,
            true,
            true,
            true,
            true,
            true,
            true,
            true,
            true,
            true,
            true,
            true,
            true
        ],
        [
            true,
            true,
            true,
            true,
            true,
            true,
            true,
            true,
            true,
            true,
            true,
            true,
            true,
            true,
            true,
            true,
            true,
            true,
            true,
            true
        ]
    ],
    "z_requirements_driver_loc": [
        [
            true,
            true,
            true,
            true,
            true,
            true,
            true,
            true,
            true,
            true,
            true,
            true
        ],
        [
            true,
            true,
            true,
            true,
            true,
            true,
            true,
            true,
            true,
            true,
            true,
            true
        ]
    ]
}